pydtmdl/__init__.py
pydtmdl/utils.py
pydtmdl/base/__init__.py
pydtmdl/base/dtm.py
pydtmdl/base/wcs.py
pydtmdl/base/wms.py
pydtmdl/providers/__init__.py
pydtmdl/providers/arctic.py
pydtmdl/providers/baden.py
pydtmdl/providers/bavaria.py
pydtmdl/providers/canada.py
pydtmdl/providers/czech.py
pydtmdl/providers/czech_dmr5g.py
pydtmdl/providers/denmark.py
pydtmdl/providers/england.py
pydtmdl/providers/finland.py
pydtmdl/providers/flanders.py
pydtmdl/providers/france.py
pydtmdl/providers/hessen.py
pydtmdl/providers/italy.py
pydtmdl/providers/lithuania.py
pydtmdl/providers/mv.py
pydtmdl/providers/niedersachsen.py
pydtmdl/providers/norway.py
pydtmdl/providers/nrw.py
pydtmdl/providers/rema.py
pydtmdl/providers/sachsenanhalt.py
pydtmdl/providers/scotland.py
pydtmdl/providers/spain.py
pydtmdl/providers/srtm.py
pydtmdl/providers/sweden.py
pydtmdl/providers/switzerland.py
pydtmdl/providers/thuringia.py
pydtmdl/providers/usgs_wcs.py
pydtmdl/providers/wales.py
pydtmdl-0.0.9.dist-info/licenses/LICENSE.md
pydtmdl-0.0.9.dist-info/METADATA
pydtmdl-0.0.9.dist-info/WHEEL
pydtmdl-0.0.9.dist-info/top_level.txt
pydtmdl-0.0.9.dist-info/RECORD
