Metadata-Version: 2.4
Name: pydtmdl
Version: 0.0.9
Summary: Python library to download DTM data from various providers.
Author-email: iwatkot <iwatkot@gmail.com>
License: GNU Affero General Public License v3
Project-URL: Homepage, https://github.com/iwatkot/pydtmdl
Project-URL: Repository, https://github.com/iwatkot/pydtmdl
Keywords: dtm,digital terrain model,elevation,geospatial
Classifier: Programming Language :: Python :: 3.11
Classifier: Programming Language :: Python :: 3.12
Classifier: License :: OSI Approved :: GNU Affero General Public License v3
Classifier: Operating System :: OS Independent
License-File: LICENSE.md
Requires-Dist: numpy
Requires-Dist: rasterio
Requires-Dist: requests
Requires-Dist: pydantic
Requires-Dist: tqdm
Requires-Dist: osmnx
Requires-Dist: owslib
Dynamic: license-file
